pyamo/__init__.py
pyamo/admin.py
pyamo/cli.py
pyamo/logs.py
pyamo/lzma.py
pyamo/queue.py
pyamo/review.py
pyamo/service.py
pyamo/session.py
pyamo/utils.py
pyamo/validation.py
pyamo-2.0.0.dist-info/LICENSE
pyamo-2.0.0.dist-info/METADATA
pyamo-2.0.0.dist-info/WHEEL
pyamo-2.0.0.dist-info/entry_points.txt
pyamo-2.0.0.dist-info/top_level.txt
pyamo-2.0.0.dist-info/RECORD
