Metadata-Version: 2.1
Name: pyamo
Version: 2.0.0
Summary: Access reviewer services on addons.mozilla.org from python
Home-page: https://github.com/kewisch/pyamo
Author: Philipp Kewisch
Author-email: mozilla@kewis.ch
License: MPL-2.0
Project-URL: Bug Tracker, https://github.com/kewisch/pyamo/issues
Keywords: amo mozilla add-ons
Platform: UNKNOWN
Classifier: License :: OSI Approved :: Mozilla Public License 2.0 (MPL 2.0)
Classifier: Development Status :: 4 - Beta
Classifier: Programming Language :: Python :: 3
Classifier: Environment :: Console
Classifier: Topic :: Utilities
Requires-Python: >=3
License-File: LICENSE
Requires-Dist: PyFxA (>=0.7.0)
Requires-Dist: python-magic
Requires-Dist: requests
Requires-Dist: lxml
Requires-Dist: mozrunner
Requires-Dist: cssselect
Requires-Dist: cmp-version
Requires-Dist: arghandler (>=1.0.3)
Requires-Dist: pylzma
Requires-Dist: pytz
Requires-Dist: tzlocal
Requires-Dist: python-dateutil
